[
  {
    "name": "abjad",
    "full_name": "metatronslove/abjad",
    "private": false,
    "updated_at": "2025-10-21T04:26:45.420183+00:00"
  },
  {
    "name": "abjad-magic-square-checker",
    "full_name": "metatronslove/abjad-magic-square-checker",
    "private": false,
    "updated_at": "2025-10-21T04:26:46.945712+00:00"
  },
  {
    "name": "auto-clicker",
    "full_name": "metatronslove/auto-clicker",
    "private": false,
    "updated_at": "2025-10-21T04:26:48.411020+00:00"
  },
  {
    "name": "bash-installer-genearator",
    "full_name": "metatronslove/bash-installer-genearator",
    "private": false,
    "updated_at": "2025-10-21T04:26:49.843266+00:00"
  },
  {
    "name": "batch-and-bash-conversion-scripts-for-ffmpeg",
    "full_name": "metatronslove/batch-and-bash-conversion-scripts-for-ffmpeg",
    "private": false,
    "updated_at": "2025-10-21T04:26:51.281518+00:00"
  },
  {
    "name": "CPU-Only-Local-GPT-Neo-Test-Server-AI-GUI",
    "full_name": "metatronslove/CPU-Only-Local-GPT-Neo-Test-Server-AI-GUI",
    "private": false,
    "updated_at": "2025-10-21T04:26:52.715242+00:00"
  },
  {
    "name": "cuma13",
    "full_name": "metatronslove/cuma13",
    "private": false,
    "updated_at": "2025-10-21T04:26:54.138189+00:00"
  },
  {
    "name": "flat-earth-celestial-tracker",
    "full_name": "metatronslove/flat-earth-celestial-tracker",
    "private": false,
    "updated_at": "2025-10-21T04:26:55.565721+00:00"
  },
  {
    "name": "github-repo-traffic-viewer",
    "full_name": "metatronslove/github-repo-traffic-viewer",
    "private": false,
    "updated_at": "2025-10-21T04:26:57.030036+00:00"
  },
  {
    "name": "Ilce-isimleri-Numerolojik-Kayitlari",
    "full_name": "metatronslove/Ilce-isimleri-Numerolojik-Kayitlari",
    "private": false,
    "updated_at": "2025-10-21T04:26:58.425427+00:00"
  },
  {
    "name": "isimler-ve-ebced-degerleri",
    "full_name": "metatronslove/isimler-ve-ebced-degerleri",
    "private": false,
    "updated_at": "2025-10-21T04:26:59.885604+00:00"
  },
  {
    "name": "kilo-kontrol-kayitlari",
    "full_name": "metatronslove/kilo-kontrol-kayitlari",
    "private": false,
    "updated_at": "2025-10-21T04:27:01.288191+00:00"
  },
  {
    "name": "Letter-Count-Tool",
    "full_name": "metatronslove/Letter-Count-Tool",
    "private": false,
    "updated_at": "2025-10-21T04:27:02.736224+00:00"
  },
  {
    "name": "liliths-luck",
    "full_name": "metatronslove/liliths-luck",
    "private": false,
    "updated_at": "2025-10-21T04:27:04.173636+00:00"
  },
  {
    "name": "local-previewer-html",
    "full_name": "metatronslove/local-previewer-html",
    "private": false,
    "updated_at": "2025-10-21T04:27:05.606620+00:00"
  },
  {
    "name": "magic-square-generator",
    "full_name": "metatronslove/magic-square-generator",
    "private": false,
    "updated_at": "2025-10-21T04:27:07.031691+00:00"
  },
  {
    "name": "metatronslove",
    "full_name": "metatronslove/metatronslove",
    "private": false,
    "updated_at": "2025-10-21T04:27:08.476733+00:00"
  },
  {
    "name": "NumberFansBot",
    "full_name": "metatronslove/NumberFansBot",
    "private": false,
    "updated_at": "2025-10-21T04:27:09.916960+00:00"
  },
  {
    "name": "occultabjadcalculator",
    "full_name": "metatronslove/occultabjadcalculator",
    "private": false,
    "updated_at": "2025-10-21T04:27:12.000592+00:00"
  },
  {
    "name": "offline-downloader-script-and-gui",
    "full_name": "metatronslove/offline-downloader-script-and-gui",
    "private": false,
    "updated_at": "2025-10-21T04:27:13.446998+00:00"
  },
  {
    "name": "okult-ebced-hesaplayici-cordova-android-app",
    "full_name": "metatronslove/okult-ebced-hesaplayici-cordova-android-app",
    "private": false,
    "updated_at": "2025-10-21T04:27:14.877943+00:00"
  },
  {
    "name": "reversi",
    "full_name": "metatronslove/reversi",
    "private": false,
    "updated_at": "2025-10-21T04:27:16.352779+00:00"
  },
  {
    "name": "sayiya-zar-at",
    "full_name": "metatronslove/sayiya-zar-at",
    "private": false,
    "updated_at": "2025-10-21T04:27:17.770337+00:00"
  },
  {
    "name": "sihirli-kare-olusturucu-cordova-android-app",
    "full_name": "metatronslove/sihirli-kare-olusturucu-cordova-android-app",
    "private": false,
    "updated_at": "2025-10-21T04:27:19.253600+00:00"
  },
  {
    "name": "Vanilla-JavaScript-Numerology-Calculator",
    "full_name": "metatronslove/Vanilla-JavaScript-Numerology-Calculator",
    "private": false,
    "updated_at": "2025-10-21T04:27:20.689559+00:00"
  },
  {
    "name": "witchy",
    "full_name": "metatronslove/witchy",
    "private": false,
    "updated_at": "2025-10-21T04:27:22.126581+00:00"
  },
  {
    "name": "YouTube-sohbet-asistan-",
    "full_name": "metatronslove/YouTube-sohbet-asistan-",
    "private": false,
    "updated_at": "2025-10-21T04:27:23.557472+00:00"
  }
]