[
  {
    "name": "abjad",
    "full_name": "metatronslove/abjad",
    "private": false,
    "updated_at": "2025-08-19T19:17:42.012295+00:00"
  },
  {
    "name": "abjad-magic-square-checker",
    "full_name": "metatronslove/abjad-magic-square-checker",
    "private": false,
    "updated_at": "2025-08-19T19:17:43.436285+00:00"
  },
  {
    "name": "auto-clicker",
    "full_name": "metatronslove/auto-clicker",
    "private": false,
    "updated_at": "2025-08-19T19:17:44.880037+00:00"
  },
  {
    "name": "bash-installer-genearator",
    "full_name": "metatronslove/bash-installer-genearator",
    "private": false,
    "updated_at": "2025-08-19T19:17:46.343249+00:00"
  },
  {
    "name": "CPU-Only-Local-GPT-Neo-Test-Server-AI-GUI",
    "full_name": "metatronslove/CPU-Only-Local-GPT-Neo-Test-Server-AI-GUI",
    "private": false,
    "updated_at": "2025-08-19T19:17:47.791322+00:00"
  },
  {
    "name": "cuma13",
    "full_name": "metatronslove/cuma13",
    "private": false,
    "updated_at": "2025-08-19T19:17:49.206132+00:00"
  },
  {
    "name": "flat-earth-celestial-tracker",
    "full_name": "metatronslove/flat-earth-celestial-tracker",
    "private": false,
    "updated_at": "2025-08-19T19:17:50.643754+00:00"
  },
  {
    "name": "github-repo-traffic-viewer",
    "full_name": "metatronslove/github-repo-traffic-viewer",
    "private": false,
    "updated_at": "2025-08-19T19:17:52.065531+00:00"
  },
  {
    "name": "Ilce-isimleri-Numerolojik-Kayitlari",
    "full_name": "metatronslove/Ilce-isimleri-Numerolojik-Kayitlari",
    "private": false,
    "updated_at": "2025-08-19T19:17:53.506274+00:00"
  },
  {
    "name": "isimler-ve-ebced-degerleri",
    "full_name": "metatronslove/isimler-ve-ebced-degerleri",
    "private": false,
    "updated_at": "2025-08-19T19:17:54.944719+00:00"
  },
  {
    "name": "kilo-kontrol-kayitlari",
    "full_name": "metatronslove/kilo-kontrol-kayitlari",
    "private": false,
    "updated_at": "2025-08-19T19:17:56.397259+00:00"
  },
  {
    "name": "Letter-Count-Tool",
    "full_name": "metatronslove/Letter-Count-Tool",
    "private": false,
    "updated_at": "2025-08-19T19:17:57.855011+00:00"
  },
  {
    "name": "liliths-luck",
    "full_name": "metatronslove/liliths-luck",
    "private": false,
    "updated_at": "2025-08-19T19:17:59.268450+00:00"
  },
  {
    "name": "local-previewer-html",
    "full_name": "metatronslove/local-previewer-html",
    "private": false,
    "updated_at": "2025-08-19T19:18:00.710226+00:00"
  },
  {
    "name": "magic-square-generator",
    "full_name": "metatronslove/magic-square-generator",
    "private": false,
    "updated_at": "2025-08-19T19:18:02.187758+00:00"
  },
  {
    "name": "metatronslove",
    "full_name": "metatronslove/metatronslove",
    "private": false,
    "updated_at": "2025-08-19T19:18:03.682149+00:00"
  },
  {
    "name": "NumberFansBot",
    "full_name": "metatronslove/NumberFansBot",
    "private": false,
    "updated_at": "2025-08-19T19:18:05.134142+00:00"
  },
  {
    "name": "occultabjadcalculator",
    "full_name": "metatronslove/occultabjadcalculator",
    "private": false,
    "updated_at": "2025-08-19T19:18:06.583480+00:00"
  },
  {
    "name": "offline-downloader-script-and-gui",
    "full_name": "metatronslove/offline-downloader-script-and-gui",
    "private": false,
    "updated_at": "2025-08-19T19:18:08.080219+00:00"
  },
  {
    "name": "okult-ebced-hesaplayici-cordova-android-app",
    "full_name": "metatronslove/okult-ebced-hesaplayici-cordova-android-app",
    "private": false,
    "updated_at": "2025-08-19T19:18:09.506922+00:00"
  },
  {
    "name": "reversi",
    "full_name": "metatronslove/reversi",
    "private": false,
    "updated_at": "2025-08-19T19:18:10.998354+00:00"
  },
  {
    "name": "sayiya-zar-at",
    "full_name": "metatronslove/sayiya-zar-at",
    "private": false,
    "updated_at": "2025-08-19T19:18:12.465596+00:00"
  },
  {
    "name": "sihirli-kare-olusturucu-cordova-android-app",
    "full_name": "metatronslove/sihirli-kare-olusturucu-cordova-android-app",
    "private": false,
    "updated_at": "2025-08-19T19:18:13.924477+00:00"
  },
  {
    "name": "Vanilla-JavaScript-Numerology-Calculator",
    "full_name": "metatronslove/Vanilla-JavaScript-Numerology-Calculator",
    "private": false,
    "updated_at": "2025-08-19T19:18:15.364604+00:00"
  }
]