[
  {
    "name": "abjad",
    "full_name": "metatronslove/abjad",
    "private": false,
    "updated_at": "2025-10-10T19:17:15.310378+00:00"
  },
  {
    "name": "abjad-magic-square-checker",
    "full_name": "metatronslove/abjad-magic-square-checker",
    "private": false,
    "updated_at": "2025-10-10T19:17:16.845000+00:00"
  },
  {
    "name": "auto-clicker",
    "full_name": "metatronslove/auto-clicker",
    "private": false,
    "updated_at": "2025-10-10T19:17:18.403789+00:00"
  },
  {
    "name": "bash-installer-genearator",
    "full_name": "metatronslove/bash-installer-genearator",
    "private": false,
    "updated_at": "2025-10-10T19:17:19.936299+00:00"
  },
  {
    "name": "batch-and-bash-conversion-scripts-for-ffmpeg",
    "full_name": "metatronslove/batch-and-bash-conversion-scripts-for-ffmpeg",
    "private": false,
    "updated_at": "2025-10-10T19:17:21.632146+00:00"
  },
  {
    "name": "CPU-Only-Local-GPT-Neo-Test-Server-AI-GUI",
    "full_name": "metatronslove/CPU-Only-Local-GPT-Neo-Test-Server-AI-GUI",
    "private": false,
    "updated_at": "2025-10-10T19:17:23.191164+00:00"
  },
  {
    "name": "cuma13",
    "full_name": "metatronslove/cuma13",
    "private": false,
    "updated_at": "2025-10-10T19:17:24.737018+00:00"
  },
  {
    "name": "flat-earth-celestial-tracker",
    "full_name": "metatronslove/flat-earth-celestial-tracker",
    "private": false,
    "updated_at": "2025-10-10T19:17:26.291449+00:00"
  },
  {
    "name": "github-repo-traffic-viewer",
    "full_name": "metatronslove/github-repo-traffic-viewer",
    "private": false,
    "updated_at": "2025-10-10T19:17:27.848058+00:00"
  },
  {
    "name": "Ilce-isimleri-Numerolojik-Kayitlari",
    "full_name": "metatronslove/Ilce-isimleri-Numerolojik-Kayitlari",
    "private": false,
    "updated_at": "2025-10-10T19:17:29.393358+00:00"
  },
  {
    "name": "isimler-ve-ebced-degerleri",
    "full_name": "metatronslove/isimler-ve-ebced-degerleri",
    "private": false,
    "updated_at": "2025-10-10T19:17:30.937917+00:00"
  },
  {
    "name": "kilo-kontrol-kayitlari",
    "full_name": "metatronslove/kilo-kontrol-kayitlari",
    "private": false,
    "updated_at": "2025-10-10T19:17:32.502925+00:00"
  },
  {
    "name": "Letter-Count-Tool",
    "full_name": "metatronslove/Letter-Count-Tool",
    "private": false,
    "updated_at": "2025-10-10T19:17:34.068049+00:00"
  },
  {
    "name": "liliths-luck",
    "full_name": "metatronslove/liliths-luck",
    "private": false,
    "updated_at": "2025-10-10T19:17:35.629260+00:00"
  },
  {
    "name": "local-previewer-html",
    "full_name": "metatronslove/local-previewer-html",
    "private": false,
    "updated_at": "2025-10-10T19:17:37.282093+00:00"
  },
  {
    "name": "magic-square-generator",
    "full_name": "metatronslove/magic-square-generator",
    "private": false,
    "updated_at": "2025-10-10T19:17:38.844297+00:00"
  },
  {
    "name": "metatronslove",
    "full_name": "metatronslove/metatronslove",
    "private": false,
    "updated_at": "2025-10-10T19:17:40.793216+00:00"
  },
  {
    "name": "NumberFansBot",
    "full_name": "metatronslove/NumberFansBot",
    "private": false,
    "updated_at": "2025-10-10T19:17:42.384396+00:00"
  },
  {
    "name": "occultabjadcalculator",
    "full_name": "metatronslove/occultabjadcalculator",
    "private": false,
    "updated_at": "2025-10-10T19:17:44.148107+00:00"
  },
  {
    "name": "offline-downloader-script-and-gui",
    "full_name": "metatronslove/offline-downloader-script-and-gui",
    "private": false,
    "updated_at": "2025-10-10T19:17:45.732330+00:00"
  },
  {
    "name": "okult-ebced-hesaplayici-cordova-android-app",
    "full_name": "metatronslove/okult-ebced-hesaplayici-cordova-android-app",
    "private": false,
    "updated_at": "2025-10-10T19:17:47.329207+00:00"
  },
  {
    "name": "reversi",
    "full_name": "metatronslove/reversi",
    "private": false,
    "updated_at": "2025-10-10T19:17:48.907911+00:00"
  },
  {
    "name": "sayiya-zar-at",
    "full_name": "metatronslove/sayiya-zar-at",
    "private": false,
    "updated_at": "2025-10-10T19:17:50.514372+00:00"
  },
  {
    "name": "sihirli-kare-olusturucu-cordova-android-app",
    "full_name": "metatronslove/sihirli-kare-olusturucu-cordova-android-app",
    "private": false,
    "updated_at": "2025-10-10T19:17:52.135911+00:00"
  },
  {
    "name": "Vanilla-JavaScript-Numerology-Calculator",
    "full_name": "metatronslove/Vanilla-JavaScript-Numerology-Calculator",
    "private": false,
    "updated_at": "2025-10-10T19:17:53.796722+00:00"
  },
  {
    "name": "YouTube-sohbet-asistan-",
    "full_name": "metatronslove/YouTube-sohbet-asistan-",
    "private": false,
    "updated_at": "2025-10-10T19:17:55.337845+00:00"
  }
]