[
  {
    "name": "abjad",
    "full_name": "metatronslove/abjad",
    "private": false,
    "updated_at": "2025-05-24T10:21:23.646238+00:00"
  },
  {
    "name": "abjad-magic-square-checker",
    "full_name": "metatronslove/abjad-magic-square-checker",
    "private": false,
    "updated_at": "2025-05-24T10:21:25.021980+00:00"
  },
  {
    "name": "auto-clicker",
    "full_name": "metatronslove/auto-clicker",
    "private": false,
    "updated_at": "2025-05-24T10:21:26.402136+00:00"
  },
  {
    "name": "CPU-Only-Local-GPT-Neo-Test-Server-AI-GUI",
    "full_name": "metatronslove/CPU-Only-Local-GPT-Neo-Test-Server-AI-GUI",
    "private": false,
    "updated_at": "2025-05-24T10:21:27.771938+00:00"
  },
  {
    "name": "cuma13",
    "full_name": "metatronslove/cuma13",
    "private": false,
    "updated_at": "2025-05-24T10:21:29.151724+00:00"
  },
  {
    "name": "github-repo-traffic-viewer",
    "full_name": "metatronslove/github-repo-traffic-viewer",
    "private": false,
    "updated_at": "2025-05-24T10:21:30.519108+00:00"
  },
  {
    "name": "Ilce-isimleri-Numerolojik-Kayitlari",
    "full_name": "metatronslove/Ilce-isimleri-Numerolojik-Kayitlari",
    "private": false,
    "updated_at": "2025-05-24T10:21:31.874660+00:00"
  },
  {
    "name": "isimler-ve-ebced-degerleri",
    "full_name": "metatronslove/isimler-ve-ebced-degerleri",
    "private": false,
    "updated_at": "2025-05-24T10:21:33.246432+00:00"
  },
  {
    "name": "kilo-kontrol-kayitlari",
    "full_name": "metatronslove/kilo-kontrol-kayitlari",
    "private": false,
    "updated_at": "2025-05-24T10:21:34.624040+00:00"
  },
  {
    "name": "Letter-Count-Tool",
    "full_name": "metatronslove/Letter-Count-Tool",
    "private": false,
    "updated_at": "2025-05-24T10:21:35.981732+00:00"
  },
  {
    "name": "local-previewer-html",
    "full_name": "metatronslove/local-previewer-html",
    "private": false,
    "updated_at": "2025-05-24T10:21:37.379110+00:00"
  },
  {
    "name": "magic-square-generator",
    "full_name": "metatronslove/magic-square-generator",
    "private": false,
    "updated_at": "2025-05-24T10:21:38.751437+00:00"
  },
  {
    "name": "metatronslove",
    "full_name": "metatronslove/metatronslove",
    "private": false,
    "updated_at": "2025-05-24T10:21:40.116805+00:00"
  },
  {
    "name": "NumberFansBot",
    "full_name": "metatronslove/NumberFansBot",
    "private": false,
    "updated_at": "2025-05-24T10:21:41.480781+00:00"
  },
  {
    "name": "occultabjadcalculator",
    "full_name": "metatronslove/occultabjadcalculator",
    "private": false,
    "updated_at": "2025-05-24T10:21:42.855422+00:00"
  },
  {
    "name": "offline-downloader-script-and-gui",
    "full_name": "metatronslove/offline-downloader-script-and-gui",
    "private": false,
    "updated_at": "2025-05-24T10:21:44.216038+00:00"
  },
  {
    "name": "okult-ebced-hesaplayici-cordova-android-app",
    "full_name": "metatronslove/okult-ebced-hesaplayici-cordova-android-app",
    "private": false,
    "updated_at": "2025-05-24T10:21:45.581675+00:00"
  },
  {
    "name": "reversi",
    "full_name": "metatronslove/reversi",
    "private": false,
    "updated_at": "2025-05-24T10:21:46.970504+00:00"
  },
  {
    "name": "sihirli-kare-olusturucu-cordova-android-app",
    "full_name": "metatronslove/sihirli-kare-olusturucu-cordova-android-app",
    "private": false,
    "updated_at": "2025-05-24T10:21:48.331793+00:00"
  },
  {
    "name": "Vanilla-JavaScript-Numerology-Calculator",
    "full_name": "metatronslove/Vanilla-JavaScript-Numerology-Calculator",
    "private": false,
    "updated_at": "2025-05-24T10:21:49.689942+00:00"
  }
]