[
  {
    "name": "abjad",
    "full_name": "metatronslove/abjad",
    "private": false,
    "updated_at": "2025-10-12T14:17:42.588954+00:00"
  },
  {
    "name": "abjad-magic-square-checker",
    "full_name": "metatronslove/abjad-magic-square-checker",
    "private": false,
    "updated_at": "2025-10-12T14:17:44.163872+00:00"
  },
  {
    "name": "auto-clicker",
    "full_name": "metatronslove/auto-clicker",
    "private": false,
    "updated_at": "2025-10-12T14:17:45.696337+00:00"
  },
  {
    "name": "bash-installer-genearator",
    "full_name": "metatronslove/bash-installer-genearator",
    "private": false,
    "updated_at": "2025-10-12T14:17:47.249093+00:00"
  },
  {
    "name": "batch-and-bash-conversion-scripts-for-ffmpeg",
    "full_name": "metatronslove/batch-and-bash-conversion-scripts-for-ffmpeg",
    "private": false,
    "updated_at": "2025-10-12T14:17:48.842961+00:00"
  },
  {
    "name": "CPU-Only-Local-GPT-Neo-Test-Server-AI-GUI",
    "full_name": "metatronslove/CPU-Only-Local-GPT-Neo-Test-Server-AI-GUI",
    "private": false,
    "updated_at": "2025-10-12T14:17:50.394348+00:00"
  },
  {
    "name": "cuma13",
    "full_name": "metatronslove/cuma13",
    "private": false,
    "updated_at": "2025-10-12T14:17:51.929281+00:00"
  },
  {
    "name": "flat-earth-celestial-tracker",
    "full_name": "metatronslove/flat-earth-celestial-tracker",
    "private": false,
    "updated_at": "2025-10-12T14:17:53.476493+00:00"
  },
  {
    "name": "github-repo-traffic-viewer",
    "full_name": "metatronslove/github-repo-traffic-viewer",
    "private": false,
    "updated_at": "2025-10-12T14:17:55.064292+00:00"
  },
  {
    "name": "Ilce-isimleri-Numerolojik-Kayitlari",
    "full_name": "metatronslove/Ilce-isimleri-Numerolojik-Kayitlari",
    "private": false,
    "updated_at": "2025-10-12T14:17:56.660257+00:00"
  },
  {
    "name": "isimler-ve-ebced-degerleri",
    "full_name": "metatronslove/isimler-ve-ebced-degerleri",
    "private": false,
    "updated_at": "2025-10-12T14:17:58.362754+00:00"
  },
  {
    "name": "kilo-kontrol-kayitlari",
    "full_name": "metatronslove/kilo-kontrol-kayitlari",
    "private": false,
    "updated_at": "2025-10-12T14:17:59.911830+00:00"
  },
  {
    "name": "Letter-Count-Tool",
    "full_name": "metatronslove/Letter-Count-Tool",
    "private": false,
    "updated_at": "2025-10-12T14:18:01.552087+00:00"
  },
  {
    "name": "liliths-luck",
    "full_name": "metatronslove/liliths-luck",
    "private": false,
    "updated_at": "2025-10-12T14:18:03.096544+00:00"
  },
  {
    "name": "local-previewer-html",
    "full_name": "metatronslove/local-previewer-html",
    "private": false,
    "updated_at": "2025-10-12T14:18:04.630738+00:00"
  },
  {
    "name": "magic-square-generator",
    "full_name": "metatronslove/magic-square-generator",
    "private": false,
    "updated_at": "2025-10-12T14:18:06.151699+00:00"
  },
  {
    "name": "metatronslove",
    "full_name": "metatronslove/metatronslove",
    "private": false,
    "updated_at": "2025-10-12T14:18:07.722077+00:00"
  },
  {
    "name": "NumberFansBot",
    "full_name": "metatronslove/NumberFansBot",
    "private": false,
    "updated_at": "2025-10-12T14:18:09.238391+00:00"
  },
  {
    "name": "occultabjadcalculator",
    "full_name": "metatronslove/occultabjadcalculator",
    "private": false,
    "updated_at": "2025-10-12T14:18:10.999901+00:00"
  },
  {
    "name": "offline-downloader-script-and-gui",
    "full_name": "metatronslove/offline-downloader-script-and-gui",
    "private": false,
    "updated_at": "2025-10-12T14:18:12.546067+00:00"
  },
  {
    "name": "okult-ebced-hesaplayici-cordova-android-app",
    "full_name": "metatronslove/okult-ebced-hesaplayici-cordova-android-app",
    "private": false,
    "updated_at": "2025-10-12T14:18:14.103530+00:00"
  },
  {
    "name": "reversi",
    "full_name": "metatronslove/reversi",
    "private": false,
    "updated_at": "2025-10-12T14:18:15.667944+00:00"
  },
  {
    "name": "sayiya-zar-at",
    "full_name": "metatronslove/sayiya-zar-at",
    "private": false,
    "updated_at": "2025-10-12T14:18:17.369967+00:00"
  },
  {
    "name": "sihirli-kare-olusturucu-cordova-android-app",
    "full_name": "metatronslove/sihirli-kare-olusturucu-cordova-android-app",
    "private": false,
    "updated_at": "2025-10-12T14:18:18.894719+00:00"
  },
  {
    "name": "Vanilla-JavaScript-Numerology-Calculator",
    "full_name": "metatronslove/Vanilla-JavaScript-Numerology-Calculator",
    "private": false,
    "updated_at": "2025-10-12T14:18:20.446277+00:00"
  },
  {
    "name": "YouTube-sohbet-asistan-",
    "full_name": "metatronslove/YouTube-sohbet-asistan-",
    "private": false,
    "updated_at": "2025-10-12T14:18:22.100148+00:00"
  }
]