[
  {
    "name": "abjad",
    "full_name": "metatronslove/abjad",
    "private": false,
    "updated_at": "2025-08-29T18:27:58.279450+00:00"
  },
  {
    "name": "abjad-magic-square-checker",
    "full_name": "metatronslove/abjad-magic-square-checker",
    "private": false,
    "updated_at": "2025-08-29T18:27:59.702600+00:00"
  },
  {
    "name": "auto-clicker",
    "full_name": "metatronslove/auto-clicker",
    "private": false,
    "updated_at": "2025-08-29T18:28:01.194299+00:00"
  },
  {
    "name": "bash-installer-genearator",
    "full_name": "metatronslove/bash-installer-genearator",
    "private": false,
    "updated_at": "2025-08-29T18:28:02.586009+00:00"
  },
  {
    "name": "CPU-Only-Local-GPT-Neo-Test-Server-AI-GUI",
    "full_name": "metatronslove/CPU-Only-Local-GPT-Neo-Test-Server-AI-GUI",
    "private": false,
    "updated_at": "2025-08-29T18:28:03.973858+00:00"
  },
  {
    "name": "cuma13",
    "full_name": "metatronslove/cuma13",
    "private": false,
    "updated_at": "2025-08-29T18:28:05.394871+00:00"
  },
  {
    "name": "flat-earth-celestial-tracker",
    "full_name": "metatronslove/flat-earth-celestial-tracker",
    "private": false,
    "updated_at": "2025-08-29T18:28:06.830429+00:00"
  },
  {
    "name": "github-repo-traffic-viewer",
    "full_name": "metatronslove/github-repo-traffic-viewer",
    "private": false,
    "updated_at": "2025-08-29T18:28:08.305376+00:00"
  },
  {
    "name": "Ilce-isimleri-Numerolojik-Kayitlari",
    "full_name": "metatronslove/Ilce-isimleri-Numerolojik-Kayitlari",
    "private": false,
    "updated_at": "2025-08-29T18:28:09.699678+00:00"
  },
  {
    "name": "isimler-ve-ebced-degerleri",
    "full_name": "metatronslove/isimler-ve-ebced-degerleri",
    "private": false,
    "updated_at": "2025-08-29T18:28:11.171093+00:00"
  },
  {
    "name": "kilo-kontrol-kayitlari",
    "full_name": "metatronslove/kilo-kontrol-kayitlari",
    "private": false,
    "updated_at": "2025-08-29T18:28:12.594723+00:00"
  },
  {
    "name": "Letter-Count-Tool",
    "full_name": "metatronslove/Letter-Count-Tool",
    "private": false,
    "updated_at": "2025-08-29T18:28:13.977046+00:00"
  },
  {
    "name": "liliths-luck",
    "full_name": "metatronslove/liliths-luck",
    "private": false,
    "updated_at": "2025-08-29T18:28:15.376950+00:00"
  },
  {
    "name": "local-previewer-html",
    "full_name": "metatronslove/local-previewer-html",
    "private": false,
    "updated_at": "2025-08-29T18:28:16.739713+00:00"
  },
  {
    "name": "magic-square-generator",
    "full_name": "metatronslove/magic-square-generator",
    "private": false,
    "updated_at": "2025-08-29T18:28:18.128456+00:00"
  },
  {
    "name": "metatronslove",
    "full_name": "metatronslove/metatronslove",
    "private": false,
    "updated_at": "2025-08-29T18:28:19.548730+00:00"
  },
  {
    "name": "NumberFansBot",
    "full_name": "metatronslove/NumberFansBot",
    "private": false,
    "updated_at": "2025-08-29T18:28:20.964390+00:00"
  },
  {
    "name": "occultabjadcalculator",
    "full_name": "metatronslove/occultabjadcalculator",
    "private": false,
    "updated_at": "2025-08-29T18:28:22.371617+00:00"
  },
  {
    "name": "offline-downloader-script-and-gui",
    "full_name": "metatronslove/offline-downloader-script-and-gui",
    "private": false,
    "updated_at": "2025-08-29T18:28:23.791567+00:00"
  },
  {
    "name": "okult-ebced-hesaplayici-cordova-android-app",
    "full_name": "metatronslove/okult-ebced-hesaplayici-cordova-android-app",
    "private": false,
    "updated_at": "2025-08-29T18:28:25.207843+00:00"
  },
  {
    "name": "reversi",
    "full_name": "metatronslove/reversi",
    "private": false,
    "updated_at": "2025-08-29T18:28:26.614968+00:00"
  },
  {
    "name": "sayiya-zar-at",
    "full_name": "metatronslove/sayiya-zar-at",
    "private": false,
    "updated_at": "2025-08-29T18:28:28.014187+00:00"
  },
  {
    "name": "sihirli-kare-olusturucu-cordova-android-app",
    "full_name": "metatronslove/sihirli-kare-olusturucu-cordova-android-app",
    "private": false,
    "updated_at": "2025-08-29T18:28:29.422743+00:00"
  },
  {
    "name": "Vanilla-JavaScript-Numerology-Calculator",
    "full_name": "metatronslove/Vanilla-JavaScript-Numerology-Calculator",
    "private": false,
    "updated_at": "2025-08-29T18:28:30.829876+00:00"
  }
]